beat/__init__.py
beat/base_model.py
beat/bidomain_model.py
beat/conductivities.py
beat/ecg.py
beat/geometry.py
beat/monodomain_model.py
beat/monodomain_solver.py
beat/odesolver.py
beat/postprocess.py
beat/single_cell.py
beat/stimulation.py
beat/units.py
beat/utils.py
beat/viz.py
beat/cellmodels/__init__.py
beat/cellmodels/beeler_reuter_1977.py
beat/cellmodels/fitzhughnagumo.py
beat/cellmodels/tentusscher_panfilov_2006/__init__.py
beat/cellmodels/tentusscher_panfilov_2006/endo.py
beat/cellmodels/tentusscher_panfilov_2006/epi.py
beat/cellmodels/tentusscher_panfilov_2006/mid.py
beat/cellmodels/torord_dyn_chloride/__init__.py
beat/cellmodels/torord_dyn_chloride/endo.py
beat/cellmodels/torord_dyn_chloride/epi.py
beat/cellmodels/torord_dyn_chloride/mid.py
fenics_beat-0.1.1.dist-info/LICENSE
fenics_beat-0.1.1.dist-info/LICENSE_dolfin_pyvista_adapter
fenics_beat-0.1.1.dist-info/METADATA
fenics_beat-0.1.1.dist-info/WHEEL
fenics_beat-0.1.1.dist-info/top_level.txt
fenics_beat-0.1.1.dist-info/RECORD
