Metadata-Version: 2.1
Name: fenics-beat
Version: 0.1.1
Summary: Library to run cardiac EP simulations
Author-email: Henrik Finsberg <henriknf@simula.no>
License: MIT
Project-URL: Homepage, https://finsberg.github.io/fenics-beat
Project-URL: Documentation, https://finsberg.github.io/fenics-beat
Project-URL: Source, https://github.com/finsberg/fenics-beat
Project-URL: Tracker, https://github.com/finsberg/fenics-beat/issues
Keywords: cardiac,electrophysiology
Requires-Python: >=3.8
License-File: LICENSE
License-File: licenses/LICENSE_dolfin_pyvista_adapter
Requires-Dist: numpy<=1.21.5
Requires-Dist: pint
Provides-Extra: all
Requires-Dist: fenics-beat[test]; extra == "all"
Requires-Dist: fenics-beat[docs]; extra == "all"
Requires-Dist: fenics-beat[pypi]; extra == "all"
Requires-Dist: fenics-beat[dev]; extra == "all"
Requires-Dist: fenics-beat[demos]; extra == "all"
Provides-Extra: demos
Requires-Dist: cardiac-geometries; extra == "demos"
Requires-Dist: ldrb; extra == "demos"
Requires-Dist: gotranx; extra == "demos"
Requires-Dist: ap-features; extra == "demos"
Requires-Dist: numba; extra == "demos"
Requires-Dist: jupyter; extra == "demos"
Requires-Dist: pyvista[all]>=0.43.0; extra == "demos"
Requires-Dist: trame-vuetify; extra == "demos"
Requires-Dist: ipywidgets; extra == "demos"
Requires-Dist: fractal-tree; extra == "demos"
Provides-Extra: dev
Requires-Dist: pdbpp; extra == "dev"
Requires-Dist: ipython; extra == "dev"
Requires-Dist: bump2version; extra == "dev"
Requires-Dist: pre-commit; extra == "dev"
Provides-Extra: docs
Requires-Dist: jupyter-book; extra == "docs"
Requires-Dist: jupytext; extra == "docs"
Requires-Dist: jupyterlab-myst; extra == "docs"
Requires-Dist: sphinxcontrib-bibtex; extra == "docs"
Requires-Dist: fenics-beat[demos]; extra == "docs"
Provides-Extra: pypi
Requires-Dist: twine; extra == "pypi"
Requires-Dist: build; extra == "pypi"
Provides-Extra: test
Requires-Dist: pytest; extra == "test"
Requires-Dist: pytest-cov; extra == "test"
Requires-Dist: gotranx; extra == "test"
Requires-Dist: numba; extra == "test"
